qsparser/__init__.py
qsparser-1.0.2.dist-info/LICENSE
qsparser-1.0.2.dist-info/METADATA
qsparser-1.0.2.dist-info/WHEEL
qsparser-1.0.2.dist-info/top_level.txt
qsparser-1.0.2.dist-info/RECORD
