Metadata-Version: 2.1
Name: qsparser
Version: 1.0.2
Summary: Query string parser with nested structure supported.
Home-page: https://github.com/fillmula/qsparser
Author: Fillmula Inc.
Author-email: victor.teo@fillmula.com
License: MIT
Platform: UNKNOWN
Requires-Python: >=3.9
License-File: LICENSE
